jupyterlab_osmd/__init__.py
jupyterlab_osmd/_version.py
jupyterlab_osmd/labextension/build_log.json
jupyterlab_osmd/labextension/package.json
jupyterlab_osmd/labextension/static/lib_index_js.7a4b135b532500a91e77.js
jupyterlab_osmd/labextension/static/lib_index_js.7a4b135b532500a91e77.js.map
jupyterlab_osmd/labextension/static/remoteEntry.3d6919edbf1488ad739d.js
jupyterlab_osmd/labextension/static/remoteEntry.3d6919edbf1488ad739d.js.map
jupyterlab_osmd/labextension/static/style.js
jupyterlab_osmd/labextension/static/style_index_js.831f4e27c21a7cc94381.js
jupyterlab_osmd/labextension/static/style_index_js.831f4e27c21a7cc94381.js.map
jupyterlab_osmd/labextension/static/vendors-node_modules_opensheetmusicdisplay_build_opensheetmusicdisplay_min_js.59f8210b677c4abeb3d4.js
jupyterlab_osmd/labextension/static/vendors-node_modules_opensheetmusicdisplay_build_opensheetmusicdisplay_min_js.59f8210b677c4abeb3d4.js.map
jupyterlab_osmd/labextension/static/vendors-node_modules_uuid_dist_esm-browser_index_js.9c0e4fb4096f3468f629.js
jupyterlab_osmd/labextension/static/vendors-node_modules_uuid_dist_esm-browser_index_js.9c0e4fb4096f3468f629.js.map
jupyterlab_osmd-0.1.2.data/data/share/jupyter/labextensions/jupyterlab-osmd/build_log.json
jupyterlab_osmd-0.1.2.data/data/share/jupyter/labextensions/jupyterlab-osmd/package.json
jupyterlab_osmd-0.1.2.data/data/share/jupyter/labextensions/jupyterlab-osmd/static/lib_index_js.7a4b135b532500a91e77.js
jupyterlab_osmd-0.1.2.data/data/share/jupyter/labextensions/jupyterlab-osmd/static/lib_index_js.7a4b135b532500a91e77.js.map
jupyterlab_osmd-0.1.2.data/data/share/jupyter/labextensions/jupyterlab-osmd/static/remoteEntry.3d6919edbf1488ad739d.js
jupyterlab_osmd-0.1.2.data/data/share/jupyter/labextensions/jupyterlab-osmd/static/remoteEntry.3d6919edbf1488ad739d.js.map
jupyterlab_osmd-0.1.2.data/data/share/jupyter/labextensions/jupyterlab-osmd/static/style.js
jupyterlab_osmd-0.1.2.dist-info/METADATA
jupyterlab_osmd-0.1.2.dist-info/WHEEL
jupyterlab_osmd-0.1.2.dist-info/licenses/LICENSE
jupyterlab_osmd-0.1.2.dist-info/RECORD
