Metadata-Version: 2.3
Name: jupyterlab_osmd
Version: 0.1.2
Summary: JupyterLab mime renderer for OpenSheetMusicDisplay
Project-URL: Homepage, https://github.com/innovationOUtside/jupyterlab-osmd
Project-URL: Bug Tracker, https://github.com/innovationOUtside/jupyterlab-osmd/issues
Project-URL: Repository, https://github.com/innovationOUtside/jupyterlab-osmd.git
Author-email: Tony Hirst <tony.hirst@gmail.com>
License: MIT License
Keywords: jupyter,jupyterlab,jupyterlab-extension
Classifier: Framework :: Jupyter
Classifier: Framework :: Jupyter :: JupyterLab
Classifier: Framework :: Jupyter :: JupyterLab :: 4
Classifier: Framework :: Jupyter :: JupyterLab :: Extensions
Classifier: Framework :: Jupyter :: JupyterLab :: Extensions :: Prebuilt
Classifier: License :: OSI Approved :: BSD License
Classifier: Programming Language :: Python
Classifier: Programming Language :: Python :: 3
Classifier: Programming Language :: Python :: 3.8
Classifier: Programming Language :: Python :: 3.9
Classifier: Programming Language :: Python :: 3.10
Classifier: Programming Language :: Python :: 3.11
Classifier: Programming Language :: Python :: 3.12
Requires-Python: >=3.8
